pyfarmsay/__init__.py
pyfarmsay/__main__.py
pyfarmsay/animals.py
pyfarmsay/pyfarmsay.py
pyfarmsay/util.py
pyfarmsay-0.1.3.dist-info/LICENSE
pyfarmsay-0.1.3.dist-info/METADATA
pyfarmsay-0.1.3.dist-info/WHEEL
pyfarmsay-0.1.3.dist-info/entry_points.txt
pyfarmsay-0.1.3.dist-info/top_level.txt
pyfarmsay-0.1.3.dist-info/RECORD
