Metadata-Version: 2.1
Name: pyfarmsay
Version: 0.1.3
Summary: An example of a package developed with pyenv, built with build using setuptools, uploaded to PyPI using twine, and distributed via pip.
Author-email: Harrison Douglass <hpd2015@nyu.edu>, Sarah Al-Towaity <sa5793@nyu.edu>, Brandon Chao <bc2872@nyu.edu>, Eduarda Martini <em4047@nyu.edu>, Michelle Lu <ml6610@nyu.edu>
License: GNU GENERAL PUBLIC LICENSE
Project-URL: Homepage, https://github.com/software-students-fall2022/python-package-exercise-project-3-team-4
Project-URL: Repository, https://github.com/software-students-fall2022/python-package-exercise-project-3-team-4
Project-URL: Bug Tracker, https://github.com/software-students-fall2022/python-package-exercise-project-3-team-4/issues
Keywords: python,package,build,tutorial
Classifier: Programming Language :: Python :: 3
Classifier: Intended Audience :: Education
Classifier: License :: OSI Approved :: GNU General Public License v3 (GPLv3)
Classifier: Operating System :: OS Independent
Requires-Python: >=3.7
License-File: LICENSE
Provides-Extra: dev
Requires-Dist: pytest ; extra == 'dev'
Requires-Dist: textwrap ; extra == 'dev'
